gri/__init__.py
gri/__main__.py
gri/abc.py
gri/console.py
gri/constants.py
gri/gerrit.py
gri/github.py
gri/label.py
gri-0.6.1.dist-info/LICENSE
gri-0.6.1.dist-info/METADATA
gri-0.6.1.dist-info/WHEEL
gri-0.6.1.dist-info/entry_points.txt
gri-0.6.1.dist-info/top_level.txt
gri-0.6.1.dist-info/RECORD
