Metadata-Version: 2.1
Name: gri
Version: 0.6.1
Summary: Git Review Interface for Gerrit and Github
Home-page: https://github.com/pycontribs/gri
Author: Sorin Sbarnea
Author-email: sorin.sbarnea@gmail.com
Maintainer: Sorin Sbarnea
Maintainer-email: sorin.sbarnea@gmail.com
License: MIT
Project-URL: Source, https://github.com/pycontribs/gri
Project-URL: Tracker, https://github.com/pycontribs/gri
Project-URL: CI, https://github.com/pycontribs/gri/actions
Keywords: gerrit,git,github,review
Platform: any
Classifier: Development Status :: 5 - Production/Stable
Classifier: Environment :: Console
Classifier: Intended Audience :: Developers
Classifier: Operating System :: OS Independent
Classifier: License :: OSI Approved :: MIT License
Classifier: Topic :: Software Development :: Testing
Classifier: Topic :: Software Development :: Libraries
Classifier: Topic :: Utilities
Classifier: Programming Language :: Python :: 3
Classifier: Programming Language :: Python :: 3.6
Classifier: Programming Language :: Python :: 3.7
Classifier: Programming Language :: Python :: 3.8
Classifier: Programming Language :: Python :: 3.9
Classifier: Topic :: Software Development :: Bug Tracking
Classifier: Topic :: Software Development :: Quality Assurance
Classifier: Topic :: Software Development :: Testing
Classifier: Topic :: Utilities
Requires-Python: >=3.6
Requires-Dist: click-help-colors (>=0.6)
Requires-Dist: click (>=7.1.2)
Requires-Dist: enrich (>=1.2.1)
Requires-Dist: pygithub
Requires-Dist: pyyaml (>=5.3.1)
Requires-Dist: requests
Requires-Dist: dataclasses ; python_version < "3.7"
